bugzilla2fedmsg.py
bugzilla2fedmsg-0.3.1.dist-info/METADATA
bugzilla2fedmsg-0.3.1.dist-info/RECORD
bugzilla2fedmsg-0.3.1.dist-info/WHEEL
bugzilla2fedmsg-0.3.1.dist-info/entry_points.txt
bugzilla2fedmsg-0.3.1.dist-info/top_level.txt
