Metadata-Version: 2.1
Name: bugzilla2fedmsg
Version: 0.3.1
Summary: Consume BZ messages over STOMP and republish to fedmsg
Home-page: https://github.com/fedora-infra/bugzilla2fedmsg
Author: Ralph Bean
Author-email: rbean@redhat.com
License: LGPLv2+
Platform: UNKNOWN
Requires-Dist: fedmsg
Requires-Dist: python-bugzilla
Requires-Dist: python-dateutil
Requires-Dist: moksha.hub
Requires-Dist: stomper
